julseb_lib_python_utils/__init__.py
julseb_lib_python_utils/add_day.py
julseb_lib_python_utils/add_month.py
julseb_lib_python_utils/add_year.py
julseb_lib_python_utils/calculate_average.py
julseb_lib_python_utils/calculate_total_sum.py
julseb_lib_python_utils/capitalize.py
julseb_lib_python_utils/convert_date.py
julseb_lib_python_utils/convert_date_short.py
julseb_lib_python_utils/convert_price.py
julseb_lib_python_utils/convert_to_email.py
julseb_lib_python_utils/convert_youtube.py
julseb_lib_python_utils/decrypt.py
julseb_lib_python_utils/delete_duplicates.py
julseb_lib_python_utils/encrypt.py
julseb_lib_python_utils/filter_object.py
julseb_lib_python_utils/format_date.py
julseb_lib_python_utils/format_hour.py
julseb_lib_python_utils/generate_numbers.py
julseb_lib_python_utils/get_first_name.py
julseb_lib_python_utils/get_initials.py
julseb_lib_python_utils/get_last_name.py
julseb_lib_python_utils/get_next_day.py
julseb_lib_python_utils/get_percentage.py
julseb_lib_python_utils/get_random.py
julseb_lib_python_utils/get_random_avatar.py
julseb_lib_python_utils/get_random_date.py
julseb_lib_python_utils/get_random_number.py
julseb_lib_python_utils/get_random_string.py
julseb_lib_python_utils/get_random_time.py
julseb_lib_python_utils/get_time_now.py
julseb_lib_python_utils/get_today.py
julseb_lib_python_utils/get_tomorrow.py
julseb_lib_python_utils/get_yesterday.py
julseb_lib_python_utils/hex_to_rgb.py
julseb_lib_python_utils/regex.py
julseb_lib_python_utils/rgb_to_hex.py
julseb_lib_python_utils/slugify.py
julseb_lib_python_utils/sort_by_frequency.py
julseb_lib_python_utils/stringify_px.py
julseb_lib_python_utils/to_base_case.py
julseb_lib_python_utils/to_camel_case.py
julseb_lib_python_utils/to_constant_case.py
julseb_lib_python_utils/to_dot_case.py
julseb_lib_python_utils/to_kebab_case.py
julseb_lib_python_utils/to_pascal_case.py
julseb_lib_python_utils/to_path_case.py
julseb_lib_python_utils/to_sentence_case.py
julseb_lib_python_utils/to_snake_case.py
julseb_lib_python_utils-1.0.2.dist-info/licenses/LICENSE
julseb_lib_python_utils-1.0.2.dist-info/METADATA
julseb_lib_python_utils-1.0.2.dist-info/WHEEL
julseb_lib_python_utils-1.0.2.dist-info/top_level.txt
julseb_lib_python_utils-1.0.2.dist-info/RECORD
